napari_spotiflow/__init__.py
napari_spotiflow/_io_hooks.py
napari_spotiflow/_predict_widget.py
napari_spotiflow/_sample_data.py
napari_spotiflow/_version.py
napari_spotiflow/napari.yaml
napari_spotiflow/utils.py
napari_spotiflow/resources/spotiflow_transp_small.png
napari_spotiflow-0.4.3.dist-info/licenses/LICENSE
napari_spotiflow-0.4.3.dist-info/METADATA
napari_spotiflow-0.4.3.dist-info/WHEEL
napari_spotiflow-0.4.3.dist-info/entry_points.txt
napari_spotiflow-0.4.3.dist-info/top_level.txt
napari_spotiflow-0.4.3.dist-info/RECORD
