Metadata-Version: 2.4
Name: napari-spotiflow
Version: 0.4.3
Summary: Napari plugin for Spotiflow
Author-email: Albert Dominguez Mantes <albert.dominguezmantes@epfl.ch>, Martin Weigert <martin.weigert@epfl.ch>
License: BSD 3-Clause License
Project-URL: Bug Tracker, https://github.com/weigertlab/napari-spotiflow/issues
Project-URL: Documentation, https://github.com/weigertlab/napari-spotiflow#README.md
Project-URL: Source Code, https://github.com/weigertlab/napari-spotiflow
Project-URL: User Support, https://github.com/weigertlab/napari-spotiflow/issues
Classifier: Development Status :: 4 - Beta
Classifier: Intended Audience :: Developers
Classifier: Framework :: napari
Classifier: Topic :: Software Development :: Testing
Classifier: Programming Language :: Python
Classifier: Programming Language :: Python :: 3
Classifier: Programming Language :: Python :: 3.9
Classifier: Programming Language :: Python :: 3.10
Classifier: Programming Language :: Python :: 3.11
Classifier: Programming Language :: Python :: 3.12
Classifier: Operating System :: OS Independent
Classifier: License :: OSI Approved :: BSD License
Requires-Python: <3.13,>=3.9
License-File: LICENSE
Requires-Dist: spotiflow
Requires-Dist: npe2
Requires-Dist: napari>=0.5
Dynamic: license-file
